exverify/__init__.py
exverify/__main__.py
exverify/convert.py
exverify/docopt.py
exverify/overdrive.py
exverify/tools.py
exverify/version.py
exverify-1.0.0.dist-info/METADATA
exverify-1.0.0.dist-info/RECORD
exverify-1.0.0.dist-info/WHEEL
exverify-1.0.0.dist-info/entry_points.txt
exverify-1.0.0.dist-info/top_level.txt
