Metadata-Version: 2.1
Name: exverify
Version: 1.0.0
Summary: UNKNOWN
Home-page: https://github.com/rubenvanstaden/exverify
Author: Ruben van Staden
Author-email: rubenvanstaden@gmail.com
License: MIT
Keywords: exverify
Platform: UNKNOWN
Requires-Dist: auron
Requires-Dist: yuna
Requires-Dist: networkx
Requires-Dist: docopt
Requires-Dist: pygmsh
Requires-Dist: pandoc
Requires-Dist: scipy
Requires-Dist: termcolor
Requires-Dist: plotly
Requires-Dist: pytest
